Users/a12345/Library/Application Scripts/com.microsoft.Excel/exceling.applescript
exceling/__init__.py
exceling/__version__.py
exceling/_xlmac.py
exceling/_xlwindows.py
exceling/cli.py
exceling/constants.py
exceling/exceling.applescript
exceling/expansion.py
exceling/mac_dict.py
exceling/main.py
exceling/quickstart.xlsm
exceling/quickstart_addin.xlam
exceling/quickstart_addin_ribbon.xlam
exceling/quickstart_standalone.xlsm
exceling/server.py
exceling/udfs.py
exceling/utils.py
exceling/addin/exceling.xlam
exceling/conversion/__init__.py
exceling/conversion/framework.py
exceling/conversion/numpy_conv.py
exceling/conversion/pandas_conv.py
exceling/conversion/standard.py
exceling/ext/__init__.py
exceling/ext/sql.py
exceling/mistune/__init__.py
exceling/mistune/block_parser.py
exceling/mistune/inline_parser.py
exceling/mistune/markdown.py
exceling/mistune/renderers.py
exceling/mistune/scanner.py
exceling/mistune/directives/__init__.py
exceling/mistune/directives/admonition.py
exceling/mistune/directives/base.py
exceling/mistune/directives/include.py
exceling/mistune/directives/toc.py
exceling/mistune/plugins/__init__.py
exceling/mistune/plugins/def_list.py
exceling/mistune/plugins/extra.py
exceling/mistune/plugins/footnotes.py
exceling/mistune/plugins/table.py
exceling/mistune/plugins/task_lists.py
exceling/pro/__init__.py
exceling/pro/embedded_code.py
exceling/pro/tables.py
exceling/pro/utils.py
exceling/pro/reports/__init__.py
exceling/pro/reports/main.py
exceling/pro/reports/markdown.py
exceling/rest/__init__.py
exceling/rest/api.py
exceling/rest/serializers.py
exceling-0.0.8.dist-info/LICENSE.txt
exceling-0.0.8.dist-info/LICENSE_PRO.txt
exceling-0.0.8.dist-info/METADATA
exceling-0.0.8.dist-info/WHEEL
exceling-0.0.8.dist-info/entry_points.txt
exceling-0.0.8.dist-info/top_level.txt
exceling-0.0.8.dist-info/RECORD
