Metadata-Version: 2.1
Name: exceling
Version: 0.0.8
Summary: Make Excel fly: Interact with Excel from Python and vice versa.
Home-page: https://www.xlwings.org
Author: Zoomer Analytics LLC
Author-email: felix.zumstein@zoomeranalytics.com
License: BSD 3-clause
Keywords: xls,excel,spreadsheet,workbook,vba,macro
Platform: Windows
Platform: Mac OS X
Classifier: Development Status :: 4 - Beta
Classifier: Operating System :: Microsoft :: Windows
Classifier: Operating System :: MacOS :: MacOS X
Classifier: Programming Language :: Python
Classifier: Programming Language :: Python :: 3
Classifier: Programming Language :: Python :: 3.6
Classifier: Programming Language :: Python :: 3.7
Classifier: Programming Language :: Python :: 3.8
Classifier: Programming Language :: Python :: 3.9
Classifier: Topic :: Office/Business :: Financial :: Spreadsheet
Classifier: License :: OSI Approved :: BSD License
Requires-Python: >=3.6
Requires-Dist: psutil (>=2.0.0)
Requires-Dist: appscript (>=1.0.1)
Provides-Extra: all
Requires-Dist: cryptography ; extra == 'all'
Requires-Dist: pandas ; extra == 'all'
Requires-Dist: matplotlib ; extra == 'all'
Requires-Dist: flask ; extra == 'all'
Requires-Dist: pillow ; extra == 'all'
Provides-Extra: pro
Requires-Dist: cryptography ; extra == 'pro'
Requires-Dist: Jinja2 ; extra == 'pro'
